ThinkSound/__init__.py
ThinkSound/data/__init__.py
ThinkSound/data/datamodule.py
ThinkSound/data/dataset.py
ThinkSound/data/utils.py
ThinkSound/inference/__init__.py
ThinkSound/inference/generation.py
ThinkSound/inference/sampling.py
ThinkSound/inference/utils.py
ThinkSound/models/__init__.py
ThinkSound/models/autoencoders.py
ThinkSound/models/blocks.py
ThinkSound/models/bottleneck.py
ThinkSound/models/codebook_patterns.py
ThinkSound/models/conditioners.py
ThinkSound/models/diffusion.py
ThinkSound/models/dit.py
ThinkSound/models/embeddings.py
ThinkSound/models/factory.py
ThinkSound/models/local_attention.py
ThinkSound/models/mmdit.py
ThinkSound/models/pretrained.py
ThinkSound/models/pretransforms.py
ThinkSound/models/transformer.py
ThinkSound/models/transformer_layers.py
ThinkSound/models/utils.py
ThinkSound/training/__init__.py
ThinkSound/training/autoencoders.py
ThinkSound/training/diffusion.py
ThinkSound/training/factory.py
ThinkSound/training/utils.py
ThinkSound/training/losses/__init__.py
ThinkSound/training/losses/auraloss.py
ThinkSound/training/losses/losses.py
data_utils/__init__.py
data_utils/extract_training_audio.py
data_utils/extract_training_video.py
data_utils/v2a_utils/__init__.py
data_utils/v2a_utils/audio_text_dataset.py
data_utils/v2a_utils/audioset_224.py
data_utils/v2a_utils/audioset_video_224.py
data_utils/v2a_utils/feature_utils_224.py
data_utils/v2a_utils/feature_utils_224_audio.py
data_utils/v2a_utils/vggsound.py
data_utils/v2a_utils/vggsound_224.py
data_utils/v2a_utils/vggsound_224_no_audio.py
data_utils/v2a_utils/vggsound_224_no_sync.py
data_utils/v2a_utils/vggsound_text.py
thinksound-0.0.19.dist-info/METADATA
thinksound-0.0.19.dist-info/WHEEL
thinksound-0.0.19.dist-info/top_level.txt
thinksound-0.0.19.dist-info/RECORD
