Metadata-Version: 2.4
Name: thinksound
Version: 0.0.19
Summary: a unified Any2Audio generation framework guided by Chain-of-Thought (CoT) reasoning
Home-page: https://github.com/liuhuadai/thinksound.git
Author: liuhuadai
Requires-Dist: aeiou==0.0.20
Requires-Dist: alias-free-torch==0.0.6
Requires-Dist: auraloss==0.4.0
Requires-Dist: descript-audio-codec==1.0.0
Requires-Dist: einops==0.7.0
Requires-Dist: einops-exts==0.0.4
Requires-Dist: ema-pytorch==0.2.3
Requires-Dist: encodec==0.1.1
Requires-Dist: gradio==3.50.0
Requires-Dist: lightning==2.5.1.post0
Requires-Dist: huggingface_hub
Requires-Dist: importlib-resources==5.12.0
Requires-Dist: k-diffusion==0.1.1
Requires-Dist: laion-clap==1.1.4
Requires-Dist: local-attention==1.8.6
Requires-Dist: opencv-python==4.11.0.86
Requires-Dist: open_clip_torch==2.32.0
Requires-Dist: pandas==2.0.2
Requires-Dist: pedalboard==0.7.4
Requires-Dist: prefigure==0.0.9
Requires-Dist: pytorch_lightning==2.1.0
Requires-Dist: PyWavelets==1.4.1
Requires-Dist: safetensors
Requires-Dist: sentencepiece==0.1.99
Requires-Dist: s3fs
Requires-Dist: omegaconf
Requires-Dist: torch==2.6.0
Requires-Dist: torchaudio>=2.0.2
Requires-Dist: torchmetrics==0.11.4
Requires-Dist: tqdm
Requires-Dist: transformers
Requires-Dist: v-diffusion-pytorch==0.0.2
Requires-Dist: vector-quantize-pytorch==1.9.14
Requires-Dist: wandb==0.15.4
Requires-Dist: webdataset==0.2.48
Requires-Dist: x-transformers==1.26.6
Dynamic: author
Dynamic: home-page
Dynamic: requires-dist
Dynamic: summary
